ricardo/__init__.py
ricardo/assets/ricardo.jpg
ricardo-69.1.1.dist-info/WHEEL
ricardo-69.1.1.dist-info/METADATA
ricardo-69.1.1.dist-info/RECORD
