Metadata-Version: 2.1
Name: ricardo
Version: 69.1.1
Summary: Ricardo. But it's Python.
Author: Predeactor
Author-email: pro.julien.mauroy@gmail.com
Requires-Python: >=3.7,<4.0
Classifier: Programming Language :: Python :: 3
Classifier: Programming Language :: Python :: 3.7
Classifier: Programming Language :: Python :: 3.8
Classifier: Programming Language :: Python :: 3.9
Classifier: Programming Language :: Python :: 3.10
Classifier: Programming Language :: Python :: 3.11
